[
  {
    "rank": 1,
    "title": "月鳞绮纪疑似不足1广",
    "heat": 1039245,
    "fun_score": 0,
    "useful_score": 0,
    "total_score": 0,
    "summary": "分析失败",
    "has_idea": false,
    "product": null,
    "reason": "fault filter abort"
  },
  {
    "rank": 2,
    "title": "与辉同行宣布全额退款",
    "heat": 772229,
    "fun_score": 0,
    "useful_score": 0,
    "total_score": 0,
    "summary": "分析失败",
    "has_idea": false,
    "product": null,
    "reason": "fault filter abort"
  },
  {
    "rank": 3,
    "title": "属于中国人的清明仪式感",
    "heat": 586618,
    "fun_score": 0,
    "useful_score": 0,
    "total_score": 0,
    "summary": "分析失败",
    "has_idea": false,
    "product": null,
    "reason": "fault filter abort"
  },
  {
    "rank": 4,
    "title": "何宣林是孟子义的大学班主任",
    "heat": 429436,
    "fun_score": 0,
    "useful_score": 0,
    "total_score": 0,
    "summary": "分析失败",
    "has_idea": false,
    "product": null,
    "reason": "fault filter abort"
  },
  {
    "rank": 5,
    "title": "美军2架黑鹰直升机被伊朗击中",
    "heat": 323077,
    "fun_score": 0,
    "useful_score": 0,
    "total_score": 0,
    "summary": "分析失败",
    "has_idea": false,
    "product": null,
    "reason": "fault filter abort"
  },
  {
    "rank": 6,
    "title": "金典和浪姐分手了",
    "heat": 314540,
    "fun_score": 0,
    "useful_score": 0,
    "total_score": 0,
    "summary": "分析失败",
    "has_idea": false,
    "product": null,
    "reason": "fault filter abort"
  },
  {
    "rank": 7,
    "title": "优思益称无力售后",
    "heat": 288134,
    "fun_score": 0,
    "useful_score": 0,
    "total_score": 0,
    "summary": "分析失败",
    "has_idea": false,
    "product": null,
    "reason": "fault filter abort"
  },
  {
    "rank": 8,
    "title": "好多人装修没有去家务化的意识",
    "heat": 286228,
    "fun_score": 0,
    "useful_score": 0,
    "total_score": 0,
    "summary": "分析失败",
    "has_idea": false,
    "product": null,
    "reason": "fault filter abort"
  },
  {
    "rank": 9,
    "title": "Uzi谈下一届乌兹杯",
    "heat": 259446,
    "fun_score": 0,
    "useful_score": 0,
    "total_score": 0,
    "summary": "分析失败",
    "has_idea": false,
    "product": null,
    "reason": "fault filter abort"
  },
  {
    "rank": 10,
    "title": "工信部紧急提醒苹果用户",
    "heat": 244352,
    "fun_score": 0,
    "useful_score": 0,
    "total_score": 0,
    "summary": "分析失败",
    "has_idea": false,
    "product": null,
    "reason": "fault filter abort"
  },
  {
    "rank": 11,
    "title": "唐艺昕因皮肤原因4年未拍戏",
    "heat": 219363,
    "fun_score": 0,
    "useful_score": 0,
    "total_score": 0,
    "summary": "分析失败",
    "has_idea": false,
    "product": null,
    "reason": "fault filter abort"
  },
  {
    "rank": 12,
    "title": "孙俪新剧就这样官宣了",
    "heat": 216784,
    "fun_score": 0,
    "useful_score": 0,
    "total_score": 0,
    "summary": "分析失败",
    "has_idea": false,
    "product": null,
    "reason": "fault filter abort"
  },
  {
    "rank": 13,
    "title": "19岁少女柬埔寨失联事件迎反转",
    "heat": 184641,
    "fun_score": 0,
    "useful_score": 0,
    "total_score": 0,
    "summary": "分析失败",
    "has_idea": false,
    "product": null,
    "reason": "fault filter abort"
  },
  {
    "rank": 14,
    "title": "男子拔掉祖坟旁槟榔苗被判刑",
    "heat": 173455,
    "fun_score": 0,
    "useful_score": 0,
    "total_score": 0,
    "summary": "分析失败",
    "has_idea": false,
    "product": null,
    "reason": "fault filter abort"
  },
  {
    "rank": 15,
    "title": "带师生徒步祭英烈校领导步数76000",
    "heat": 173443,
    "fun_score": 0,
    "useful_score": 0,
    "total_score": 0,
    "summary": "分析失败",
    "has_idea": false,
    "product": null,
    "reason": "fault filter abort"
  }
]