[
  {
    "rank": 1,
    "title": "官方通报网传妈祖巡游换童事件",
    "heat": 2314069,
    "fun_score": 0,
    "useful_score": 0,
    "total_score": 0,
    "summary": "分析失败",
    "has_idea": false,
    "product": null,
    "reason": "Error code: 401 - {'error': {'type': 'authentication_error', 'code': '401', 'message': 'Incorrect API key provided. Please visit https://console.pipellm.ai/account/api-keys to find your API key.'}}"
  },
  {
    "rank": 2,
    "title": "谷爱凌金牌",
    "heat": 1204044,
    "fun_score": 0,
    "useful_score": 0,
    "total_score": 0,
    "summary": "分析失败",
    "has_idea": false,
    "product": null,
    "reason": "Error code: 401 - {'error': {'type': 'authentication_error', 'code': '401', 'message': 'Incorrect API key provided. Please visit https://console.pipellm.ai/account/api-keys to find your API key.'}}"
  },
  {
    "rank": 3,
    "title": "2026新春走基层",
    "heat": 765133,
    "fun_score": 0,
    "useful_score": 0,
    "total_score": 0,
    "summary": "分析失败",
    "has_idea": false,
    "product": null,
    "reason": "Error code: 401 - {'error': {'type': 'authentication_error', 'code': '401', 'message': 'Incorrect API key provided. Please visit https://console.pipellm.ai/account/api-keys to find your API key.'}}"
  },
  {
    "rank": 4,
    "title": "虞书欣何与 神仙肉",
    "heat": 655901,
    "fun_score": 0,
    "useful_score": 0,
    "total_score": 0,
    "summary": "分析失败",
    "has_idea": false,
    "product": null,
    "reason": "Error code: 401 - {'error': {'type': 'authentication_error', 'code': '401', 'message': 'Incorrect API key provided. Please visit https://console.pipellm.ai/account/api-keys to find your API key.'}}"
  },
  {
    "rank": 5,
    "title": "谷爱凌追平王濛冬奥奖牌纪录",
    "heat": 514956,
    "fun_score": 0,
    "useful_score": 0,
    "total_score": 0,
    "summary": "分析失败",
    "has_idea": false,
    "product": null,
    "reason": "Error code: 401 - {'error': {'type': 'authentication_error', 'code': '401', 'message': 'Incorrect API key provided. Please visit https://console.pipellm.ai/account/api-keys to find your API key.'}}"
  },
  {
    "rank": 6,
    "title": "谷爱凌唱国歌",
    "heat": 491241,
    "fun_score": 0,
    "useful_score": 0,
    "total_score": 0,
    "summary": "分析失败",
    "has_idea": false,
    "product": null,
    "reason": "Error code: 401 - {'error': {'type': 'authentication_error', 'code': '401', 'message': 'Incorrect API key provided. Please visit https://console.pipellm.ai/account/api-keys to find your API key.'}}"
  },
  {
    "rank": 7,
    "title": "太原出现疫情系谣言",
    "heat": 0,
    "fun_score": 0,
    "useful_score": 0,
    "total_score": 0,
    "summary": "分析失败",
    "has_idea": false,
    "product": null,
    "reason": "Error code: 401 - {'error': {'type': 'authentication_error', 'code': '401', 'message': 'Incorrect API key provided. Please visit https://console.pipellm.ai/account/api-keys to find your API key.'}}"
  },
  {
    "rank": 8,
    "title": "王濛祝贺谷爱凌李方慧",
    "heat": 482684,
    "fun_score": 0,
    "useful_score": 0,
    "total_score": 0,
    "summary": "分析失败",
    "has_idea": false,
    "product": null,
    "reason": "Error code: 401 - {'error': {'type': 'authentication_error', 'code': '401', 'message': 'Incorrect API key provided. Please visit https://console.pipellm.ai/account/api-keys to find your API key.'}}"
  },
  {
    "rank": 9,
    "title": "谷爱凌第三滑94.75分",
    "heat": 465977,
    "fun_score": 0,
    "useful_score": 0,
    "total_score": 0,
    "summary": "分析失败",
    "has_idea": false,
    "product": null,
    "reason": "Error code: 401 - {'error': {'type': 'authentication_error', 'code': '401', 'message': 'Incorrect API key provided. Please visit https://console.pipellm.ai/account/api-keys to find your API key.'}}"
  },
  {
    "rank": 10,
    "title": "张凌赫 刺棠",
    "heat": 368158,
    "fun_score": 0,
    "useful_score": 0,
    "total_score": 0,
    "summary": "分析失败",
    "has_idea": false,
    "product": null,
    "reason": "Error code: 401 - {'error': {'type': 'authentication_error', 'code': '401', 'message': 'Incorrect API key provided. Please visit https://console.pipellm.ai/account/api-keys to find your API key.'}}"
  },
  {
    "rank": 11,
    "title": "女子U型场地决赛",
    "heat": 365019,
    "fun_score": 0,
    "useful_score": 0,
    "total_score": 0,
    "summary": "分析失败",
    "has_idea": false,
    "product": null,
    "reason": "Error code: 401 - {'error': {'type': 'authentication_error', 'code': '401', 'message': 'Incorrect API key provided. Please visit https://console.pipellm.ai/account/api-keys to find your API key.'}}"
  },
  {
    "rank": 12,
    "title": "孟子义李昀锐 四搭",
    "heat": 358542,
    "fun_score": 0,
    "useful_score": 0,
    "total_score": 0,
    "summary": "分析失败",
    "has_idea": false,
    "product": null,
    "reason": "Error code: 401 - {'error': {'type': 'authentication_error', 'code': '401', 'message': 'Incorrect API key provided. Please visit https://console.pipellm.ai/account/api-keys to find your API key.'}}"
  },
  {
    "rank": 13,
    "title": "白鹿这眼线是自己画的吧",
    "heat": 356524,
    "fun_score": 0,
    "useful_score": 0,
    "total_score": 0,
    "summary": "分析失败",
    "has_idea": false,
    "product": null,
    "reason": "Error code: 401 - {'error': {'type': 'authentication_error', 'code': '401', 'message': 'Incorrect API key provided. Please visit https://console.pipellm.ai/account/api-keys to find your API key.'}}"
  },
  {
    "rank": 14,
    "title": "中国队5金4银6铜收官",
    "heat": 347232,
    "fun_score": 0,
    "useful_score": 0,
    "total_score": 0,
    "summary": "分析失败",
    "has_idea": false,
    "product": null,
    "reason": "Error code: 401 - {'error': {'type': 'authentication_error', 'code': '401', 'message': 'Incorrect API key provided. Please visit https://console.pipellm.ai/account/api-keys to find your API key.'}}"
  },
  {
    "rank": 15,
    "title": "谷爱凌U池卫冕成功",
    "heat": 305185,
    "fun_score": 0,
    "useful_score": 0,
    "total_score": 0,
    "summary": "分析失败",
    "has_idea": false,
    "product": null,
    "reason": "Error code: 401 - {'error': {'type': 'authentication_error', 'code': '401', 'message': 'Incorrect API key provided. Please visit https://console.pipellm.ai/account/api-keys to find your API key.'}}"
  }
]