[
  {
    "rank": 1,
    "title": "孙颖莎成国乒削球扫雷手",
    "heat": 1114715,
    "fun_score": 0,
    "useful_score": 0,
    "total_score": 0,
    "summary": "分析失败",
    "has_idea": false,
    "product": null,
    "reason": "fault filter abort"
  },
  {
    "rank": 2,
    "title": "绿源电动车 擦边",
    "heat": 793377,
    "fun_score": 0,
    "useful_score": 0,
    "total_score": 0,
    "summary": "分析失败",
    "has_idea": false,
    "product": null,
    "reason": "fault filter abort"
  },
  {
    "rank": 3,
    "title": "全国两优一先表彰名单公布",
    "heat": 614463,
    "fun_score": 0,
    "useful_score": 0,
    "total_score": 0,
    "summary": "分析失败",
    "has_idea": false,
    "product": null,
    "reason": "fault filter abort"
  },
  {
    "rank": 4,
    "title": "人工智能冲击婚纱影楼",
    "heat": 604914,
    "fun_score": 0,
    "useful_score": 0,
    "total_score": 0,
    "summary": "分析失败",
    "has_idea": false,
    "product": null,
    "reason": "fault filter abort"
  },
  {
    "rank": 5,
    "title": "野狗骨头",
    "heat": 591551,
    "fun_score": 0,
    "useful_score": 0,
    "total_score": 0,
    "summary": "分析失败",
    "has_idea": false,
    "product": null,
    "reason": "fault filter abort"
  },
  {
    "rank": 6,
    "title": "虞书欣给剧本包书皮",
    "heat": 481537,
    "fun_score": 0,
    "useful_score": 0,
    "total_score": 0,
    "summary": "分析失败",
    "has_idea": false,
    "product": null,
    "reason": "fault filter abort"
  },
  {
    "rank": 7,
    "title": "哈兰德每天摄入6000卡热量",
    "heat": 481358,
    "fun_score": 0,
    "useful_score": 0,
    "total_score": 0,
    "summary": "分析失败",
    "has_idea": false,
    "product": null,
    "reason": "fault filter abort"
  },
  {
    "rank": 8,
    "title": "日本防相竟放话要中国给理由",
    "heat": 478070,
    "fun_score": 0,
    "useful_score": 0,
    "total_score": 0,
    "summary": "分析失败",
    "has_idea": false,
    "product": null,
    "reason": "fault filter abort"
  },
  {
    "rank": 9,
    "title": "暑期教育部高校学生资助热线开通",
    "heat": 474711,
    "fun_score": 0,
    "useful_score": 0,
    "total_score": 0,
    "summary": "分析失败",
    "has_idea": false,
    "product": null,
    "reason": "fault filter abort"
  },
  {
    "rank": 10,
    "title": "小米高层重大调整",
    "heat": 473341,
    "fun_score": 0,
    "useful_score": 0,
    "total_score": 0,
    "summary": "分析失败",
    "has_idea": false,
    "product": null,
    "reason": "fault filter abort"
  },
  {
    "rank": 11,
    "title": "霍震霆回应霍启山娜然结婚传闻",
    "heat": 470200,
    "fun_score": 0,
    "useful_score": 0,
    "total_score": 0,
    "summary": "分析失败",
    "has_idea": false,
    "product": null,
    "reason": "fault filter abort"
  },
  {
    "rank": 12,
    "title": "恋与深空",
    "heat": 467741,
    "fun_score": 0,
    "useful_score": 0,
    "total_score": 0,
    "summary": "分析失败",
    "has_idea": false,
    "product": null,
    "reason": "fault filter abort"
  },
  {
    "rank": 13,
    "title": "真实的乡镇公务员是这样的",
    "heat": 465201,
    "fun_score": 0,
    "useful_score": 0,
    "total_score": 0,
    "summary": "分析失败",
    "has_idea": false,
    "product": null,
    "reason": "fault filter abort"
  },
  {
    "rank": 14,
    "title": "丁禹兮 姜珮瑶",
    "heat": 463665,
    "fun_score": 0,
    "useful_score": 0,
    "total_score": 0,
    "summary": "分析失败",
    "has_idea": false,
    "product": null,
    "reason": "fault filter abort"
  },
  {
    "rank": 15,
    "title": "李金铭现身",
    "heat": 461851,
    "fun_score": 0,
    "useful_score": 0,
    "total_score": 0,
    "summary": "分析失败",
    "has_idea": false,
    "product": null,
    "reason": "fault filter abort"
  }
]