[
  {
    "rank": 1,
    "title": "逐玉",
    "heat": 1078663,
    "fun_score": 0,
    "useful_score": 0,
    "total_score": 0,
    "summary": "分析失败",
    "has_idea": false,
    "product": null,
    "reason": "fault filter abort"
  },
  {
    "rank": 2,
    "title": "中国学生开始卷海外考公了",
    "heat": 796169,
    "fun_score": 0,
    "useful_score": 0,
    "total_score": 0,
    "summary": "分析失败",
    "has_idea": false,
    "product": null,
    "reason": "fault filter abort"
  },
  {
    "rank": 3,
    "title": "北斗导航机器挖坑在沙漠5秒种1棵树",
    "heat": 620567,
    "fun_score": 0,
    "useful_score": 0,
    "total_score": 0,
    "summary": "分析失败",
    "has_idea": false,
    "product": null,
    "reason": "fault filter abort"
  },
  {
    "rank": 4,
    "title": "齐本宫",
    "heat": 620387,
    "fun_score": 0,
    "useful_score": 0,
    "total_score": 0,
    "summary": "分析失败",
    "has_idea": false,
    "product": null,
    "reason": "fault filter abort"
  },
  {
    "rank": 5,
    "title": "698元海蓝之谜只有瓶子是真的",
    "heat": 618751,
    "fun_score": 0,
    "useful_score": 0,
    "total_score": 0,
    "summary": "分析失败",
    "has_idea": false,
    "product": null,
    "reason": "fault filter abort"
  },
  {
    "rank": 6,
    "title": "黄金怎么不涨反跌",
    "heat": 616349,
    "fun_score": 0,
    "useful_score": 0,
    "total_score": 0,
    "summary": "分析失败",
    "has_idea": false,
    "product": null,
    "reason": "fault filter abort"
  },
  {
    "rank": 7,
    "title": "伊朗为拉里贾尼举行葬礼",
    "heat": 614896,
    "fun_score": 0,
    "useful_score": 0,
    "total_score": 0,
    "summary": "分析失败",
    "has_idea": false,
    "product": null,
    "reason": "fault filter abort"
  },
  {
    "rank": 8,
    "title": "白玉兰官宣6月26日颁奖",
    "heat": 612339,
    "fun_score": 0,
    "useful_score": 0,
    "total_score": 0,
    "summary": "分析失败",
    "has_idea": false,
    "product": null,
    "reason": "fault filter abort"
  },
  {
    "rank": 9,
    "title": "BLG对战G2",
    "heat": 609919,
    "fun_score": 0,
    "useful_score": 0,
    "total_score": 0,
    "summary": "分析失败",
    "has_idea": false,
    "product": null,
    "reason": "fault filter abort"
  },
  {
    "rank": 10,
    "title": "周启豪获世乒赛参赛名额",
    "heat": 608600,
    "fun_score": 0,
    "useful_score": 0,
    "total_score": 0,
    "summary": "分析失败",
    "has_idea": false,
    "product": null,
    "reason": "fault filter abort"
  },
  {
    "rank": 11,
    "title": "徐若晗 挂脸",
    "heat": 606945,
    "fun_score": 0,
    "useful_score": 0,
    "total_score": 0,
    "summary": "分析失败",
    "has_idea": false,
    "product": null,
    "reason": "fault filter abort"
  },
  {
    "rank": 12,
    "title": "逐玉预告",
    "heat": 604770,
    "fun_score": 0,
    "useful_score": 0,
    "total_score": 0,
    "summary": "分析失败",
    "has_idea": false,
    "product": null,
    "reason": "fault filter abort"
  },
  {
    "rank": 13,
    "title": "金价",
    "heat": 604587,
    "fun_score": 0,
    "useful_score": 0,
    "total_score": 0,
    "summary": "分析失败",
    "has_idea": false,
    "product": null,
    "reason": "fault filter abort"
  },
  {
    "rank": 14,
    "title": "早期田曦薇 真人bjd",
    "heat": 601537,
    "fun_score": 0,
    "useful_score": 0,
    "total_score": 0,
    "summary": "分析失败",
    "has_idea": false,
    "product": null,
    "reason": "fault filter abort"
  },
  {
    "rank": 15,
    "title": "美联储",
    "heat": 489693,
    "fun_score": 0,
    "useful_score": 0,
    "total_score": 0,
    "summary": "分析失败",
    "has_idea": false,
    "product": null,
    "reason": "fault filter abort"
  }
]