[
  {
    "rank": 1,
    "title": "提醒在伊朗的中国公民尽快撤离",
    "heat": 1167255,
    "fun_score": 0,
    "useful_score": 0,
    "total_score": 0,
    "summary": "分析失败",
    "has_idea": false,
    "product": null,
    "reason": "Error code: 401 - {'error': {'type': 'authentication_error', 'code': '401', 'message': 'Incorrect API key provided. Please visit https://console.pipellm.ai/account/api-keys to find your API key.'}}"
  },
  {
    "rank": 2,
    "title": "草莓价格跌至1元一斤",
    "heat": 832813,
    "fun_score": 0,
    "useful_score": 0,
    "total_score": 0,
    "summary": "分析失败",
    "has_idea": false,
    "product": null,
    "reason": "Error code: 401 - {'error': {'type': 'authentication_error', 'code': '401', 'message': 'Incorrect API key provided. Please visit https://console.pipellm.ai/account/api-keys to find your API key.'}}"
  },
  {
    "rank": 3,
    "title": "关注2026全国两会",
    "heat": 696599,
    "fun_score": 0,
    "useful_score": 0,
    "total_score": 0,
    "summary": "分析失败",
    "has_idea": false,
    "product": null,
    "reason": "Error code: 401 - {'error': {'type': 'authentication_error', 'code': '401', 'message': 'Incorrect API key provided. Please visit https://console.pipellm.ai/account/api-keys to find your API key.'}}"
  },
  {
    "rank": 4,
    "title": "Gucci直播",
    "heat": 671736,
    "fun_score": 0,
    "useful_score": 0,
    "total_score": 0,
    "summary": "分析失败",
    "has_idea": false,
    "product": null,
    "reason": "Error code: 401 - {'error': {'type': 'authentication_error', 'code': '401', 'message': 'Incorrect API key provided. Please visit https://console.pipellm.ai/account/api-keys to find your API key.'}}"
  },
  {
    "rank": 5,
    "title": "00后员工年薪80万是老板的6倍",
    "heat": 321006,
    "fun_score": 0,
    "useful_score": 0,
    "total_score": 0,
    "summary": "分析失败",
    "has_idea": false,
    "product": null,
    "reason": "Error code: 401 - {'error': {'type': 'authentication_error', 'code': '401', 'message': 'Incorrect API key provided. Please visit https://console.pipellm.ai/account/api-keys to find your API key.'}}"
  },
  {
    "rank": 6,
    "title": "纯真年代的爱情",
    "heat": 307840,
    "fun_score": 0,
    "useful_score": 0,
    "total_score": 0,
    "summary": "分析失败",
    "has_idea": false,
    "product": null,
    "reason": "Error code: 401 - {'error': {'type': 'authentication_error', 'code': '401', 'message': 'Incorrect API key provided. Please visit https://console.pipellm.ai/account/api-keys to find your API key.'}}"
  },
  {
    "rank": 7,
    "title": "孕妇为引流深夜路边直播谎称求救",
    "heat": 0,
    "fun_score": 0,
    "useful_score": 0,
    "total_score": 0,
    "summary": "分析失败",
    "has_idea": false,
    "product": null,
    "reason": "Error code: 401 - {'error': {'type': 'authentication_error', 'code': '401', 'message': 'Incorrect API key provided. Please visit https://console.pipellm.ai/account/api-keys to find your API key.'}}"
  },
  {
    "rank": 8,
    "title": "退房的时候前台拿了个徐福记的糖纸",
    "heat": 276704,
    "fun_score": 0,
    "useful_score": 0,
    "total_score": 0,
    "summary": "分析失败",
    "has_idea": false,
    "product": null,
    "reason": "Error code: 401 - {'error': {'type': 'authentication_error', 'code': '401', 'message': 'Incorrect API key provided. Please visit https://console.pipellm.ai/account/api-keys to find your API key.'}}"
  },
  {
    "rank": 9,
    "title": "RW 选错英雄",
    "heat": 230818,
    "fun_score": 0,
    "useful_score": 0,
    "total_score": 0,
    "summary": "分析失败",
    "has_idea": false,
    "product": null,
    "reason": "Error code: 401 - {'error': {'type': 'authentication_error', 'code': '401', 'message': 'Incorrect API key provided. Please visit https://console.pipellm.ai/account/api-keys to find your API key.'}}"
  },
  {
    "rank": 10,
    "title": "米哈游公布猝死员工生前工作轨迹",
    "heat": 210217,
    "fun_score": 0,
    "useful_score": 0,
    "total_score": 0,
    "summary": "分析失败",
    "has_idea": false,
    "product": null,
    "reason": "Error code: 401 - {'error': {'type': 'authentication_error', 'code': '401', 'message': 'Incorrect API key provided. Please visit https://console.pipellm.ai/account/api-keys to find your API key.'}}"
  },
  {
    "rank": 11,
    "title": "林俊杰回复张凌赫",
    "heat": 197038,
    "fun_score": 0,
    "useful_score": 0,
    "total_score": 0,
    "summary": "分析失败",
    "has_idea": false,
    "product": null,
    "reason": "Error code: 401 - {'error': {'type': 'authentication_error', 'code': '401', 'message': 'Incorrect API key provided. Please visit https://console.pipellm.ai/account/api-keys to find your API key.'}}"
  },
  {
    "rank": 12,
    "title": "伊朗",
    "heat": 196970,
    "fun_score": 0,
    "useful_score": 0,
    "total_score": 0,
    "summary": "分析失败",
    "has_idea": false,
    "product": null,
    "reason": "Error code: 401 - {'error': {'type': 'authentication_error', 'code': '401', 'message': 'Incorrect API key provided. Please visit https://console.pipellm.ai/account/api-keys to find your API key.'}}"
  },
  {
    "rank": 13,
    "title": "杨洋发文回应不让江山争议",
    "heat": 196920,
    "fun_score": 0,
    "useful_score": 0,
    "total_score": 0,
    "summary": "分析失败",
    "has_idea": false,
    "product": null,
    "reason": "Error code: 401 - {'error': {'type': 'authentication_error', 'code': '401', 'message': 'Incorrect API key provided. Please visit https://console.pipellm.ai/account/api-keys to find your API key.'}}"
  },
  {
    "rank": 14,
    "title": "美国 伊朗",
    "heat": 196866,
    "fun_score": 0,
    "useful_score": 0,
    "total_score": 0,
    "summary": "分析失败",
    "has_idea": false,
    "product": null,
    "reason": "Error code: 401 - {'error': {'type': 'authentication_error', 'code': '401', 'message': 'Incorrect API key provided. Please visit https://console.pipellm.ai/account/api-keys to find your API key.'}}"
  },
  {
    "rank": 15,
    "title": "肖战 这很齐夏",
    "heat": 196756,
    "fun_score": 0,
    "useful_score": 0,
    "total_score": 0,
    "summary": "分析失败",
    "has_idea": false,
    "product": null,
    "reason": "Error code: 401 - {'error': {'type': 'authentication_error', 'code': '401', 'message': 'Incorrect API key provided. Please visit https://console.pipellm.ai/account/api-keys to find your API key.'}}"
  }
]