[
  {
    "rank": 1,
    "title": "团播不得浓妆艳抹过度磨皮美颜",
    "heat": 1043580,
    "search_query": "团播不得浓妆艳抹过度磨皮美颜 微博热搜 2026年01月"
  },
  {
    "rank": 2,
    "title": "1克黄金竟能打造一张完整黄金婚书",
    "heat": 731650,
    "search_query": "1克黄金竟能打造一张完整黄金婚书 微博热搜 2026年01月"
  },
  {
    "rank": 3,
    "title": "2026逐梦中国",
    "heat": 594588,
    "search_query": "2026逐梦中国 微博热搜 2026年01月"
  },
  {
    "rank": 4,
    "title": "科比大女儿发文缅怀",
    "heat": 240265,
    "search_query": "科比大女儿发文缅怀 微博热搜 2026年01月"
  },
  {
    "rank": 5,
    "title": "旅日大熊猫回国走出快乐步伐",
    "heat": 183166,
    "search_query": "旅日大熊猫回国走出快乐步伐 微博热搜 2026年01月"
  },
  {
    "rank": 6,
    "title": "拒绝暗示性求助",
    "heat": 179974,
    "search_query": "拒绝暗示性求助 微博热搜 2026年01月"
  },
  {
    "rank": 7,
    "title": "金饰克价突破1620元",
    "heat": 178362,
    "search_query": "金饰克价突破1620元 微博热搜 2026年01月"
  },
  {
    "rank": 8,
    "title": "美向以色列通报对伊朗军事行动准备",
    "heat": 174694,
    "search_query": "美向以色列通报对伊朗军事行动准备 微博热搜 2026年01月"
  },
  {
    "rank": 9,
    "title": "杨瀚森勾手",
    "heat": 160784,
    "search_query": "杨瀚森勾手 微博热搜 2026年01月"
  },
  {
    "rank": 10,
    "title": "人民日报评幽灵外卖无良作坊",
    "heat": 156368,
    "search_query": "人民日报评幽灵外卖无良作坊 微博热搜 2026年01月"
  },
  {
    "rank": 11,
    "title": "肖战会去救马云",
    "heat": 154456,
    "search_query": "肖战会去救马云 微博热搜 2026年01月"
  },
  {
    "rank": 12,
    "title": "邓超减掉40斤时连嚼的力气都没有",
    "heat": 145241,
    "search_query": "邓超减掉40斤时连嚼的力气都没有 微博热搜 2026年01月"
  },
  {
    "rank": 13,
    "title": "盒马误送有毒水仙球致老人孩子中毒",
    "heat": 143395,
    "search_query": "盒马误送有毒水仙球致老人孩子中毒 微博热搜 2026年01月"
  },
  {
    "rank": 14,
    "title": "结了婚才知道纸有那么多种类型",
    "heat": 137191,
    "search_query": "结了婚才知道纸有那么多种类型 微博热搜 2026年01月"
  },
  {
    "rank": 15,
    "title": "杨紫Duang的一下就坐下去了",
    "heat": 131701,
    "search_query": "杨紫Duang的一下就坐下去了 微博热搜 2026年01月"
  }
]