[
  {
    "rank": 1,
    "title": "花少8最新阵容",
    "heat": 1298930,
    "search_query": "花少8最新阵容 微博热搜 2026年05月"
  },
  {
    "rank": 2,
    "title": "新人结婚被丢高速口路过宾利变婚车",
    "heat": 980127,
    "search_query": "新人结婚被丢高速口路过宾利变婚车 微博热搜 2026年05月"
  },
  {
    "rank": 3,
    "title": "来中国玩的外国人更多了",
    "heat": 949145,
    "search_query": "来中国玩的外国人更多了 微博热搜 2026年05月"
  },
  {
    "rank": 4,
    "title": "白鹿跑男争议 内娱综艺审美巨变",
    "heat": 948404,
    "search_query": "白鹿跑男争议 内娱综艺审美巨变 微博热搜 2026年05月"
  },
  {
    "rank": 5,
    "title": "解除台独刘世芳亲属全部职务",
    "heat": 941388,
    "search_query": "解除台独刘世芳亲属全部职务 微博热搜 2026年05月"
  },
  {
    "rank": 6,
    "title": "张杰谢娜合唱",
    "heat": 885151,
    "search_query": "张杰谢娜合唱 微博热搜 2026年05月"
  },
  {
    "rank": 7,
    "title": "网友曝三亚4只皮皮虾收费1035元",
    "heat": 791146,
    "search_query": "网友曝三亚4只皮皮虾收费1035元 微博热搜 2026年05月"
  },
  {
    "rank": 8,
    "title": "为什么户外千万不要穿迷彩",
    "heat": 552116,
    "search_query": "为什么户外千万不要穿迷彩 微博热搜 2026年05月"
  },
  {
    "rank": 9,
    "title": "三星家电退出大陆市场",
    "heat": 489552,
    "search_query": "三星家电退出大陆市场 微博热搜 2026年05月"
  },
  {
    "rank": 10,
    "title": "meiko赛后发文",
    "heat": 481619,
    "search_query": "meiko赛后发文 微博热搜 2026年05月"
  },
  {
    "rank": 11,
    "title": "EXO King",
    "heat": 481485,
    "search_query": "EXO King 微博热搜 2026年05月"
  },
  {
    "rank": 12,
    "title": "何炅躲过了所有路透",
    "heat": 481155,
    "search_query": "何炅躲过了所有路透 微博热搜 2026年05月"
  },
  {
    "rank": 13,
    "title": "钟薛高破产后508件资产207万起拍",
    "heat": 450866,
    "search_query": "钟薛高破产后508件资产207万起拍 微博热搜 2026年05月"
  },
  {
    "rank": 14,
    "title": "国乒男团进世乒赛8强",
    "heat": 446054,
    "search_query": "国乒男团进世乒赛8强 微博热搜 2026年05月"
  },
  {
    "rank": 15,
    "title": "全李酒店 全季酒店",
    "heat": 445732,
    "search_query": "全李酒店 全季酒店 微博热搜 2026年05月"
  }
]