[
  {
    "rank": 1,
    "title": "跑男收视率 浪姐没播",
    "heat": 2528684,
    "search_query": "跑男收视率 浪姐没播 微博热搜 2026年05月"
  },
  {
    "rank": 2,
    "title": "国际足联急了",
    "heat": 1358874,
    "search_query": "国际足联急了 微博热搜 2026年05月"
  },
  {
    "rank": 3,
    "title": "太空快递跑出中国加速度",
    "heat": 1179617,
    "search_query": "太空快递跑出中国加速度 微博热搜 2026年05月"
  },
  {
    "rank": 4,
    "title": "2026款丰田铂智3X权益价9.48万起",
    "heat": 0,
    "search_query": "2026款丰田铂智3X权益价9.48万起 微博热搜 2026年05月"
  },
  {
    "rank": 5,
    "title": "关晓彤终于遇到了有身高差的男主",
    "heat": 1171332,
    "search_query": "关晓彤终于遇到了有身高差的男主 微博热搜 2026年05月"
  },
  {
    "rank": 6,
    "title": "怪不得虫子总围着头顶飞",
    "heat": 1127706,
    "search_query": "怪不得虫子总围着头顶飞 微博热搜 2026年05月"
  },
  {
    "rank": 7,
    "title": "广东男篮vs北京男篮",
    "heat": 871677,
    "search_query": "广东男篮vs北京男篮 微博热搜 2026年05月"
  },
  {
    "rank": 8,
    "title": "中船科技向海图强",
    "heat": 0,
    "search_query": "中船科技向海图强 微博热搜 2026年05月"
  },
  {
    "rank": 9,
    "title": "安倍晋三遗孀陪赖清德跪日本人",
    "heat": 699155,
    "search_query": "安倍晋三遗孀陪赖清德跪日本人 微博热搜 2026年05月"
  },
  {
    "rank": 10,
    "title": "浪姐48来了",
    "heat": 676095,
    "search_query": "浪姐48来了 微博热搜 2026年05月"
  },
  {
    "rank": 11,
    "title": "伦敦世乒赛半决赛",
    "heat": 596137,
    "search_query": "伦敦世乒赛半决赛 微博热搜 2026年05月"
  },
  {
    "rank": 12,
    "title": "显微镜下的辣条",
    "heat": 592075,
    "search_query": "显微镜下的辣条 微博热搜 2026年05月"
  },
  {
    "rank": 13,
    "title": "疑似加到了孙怡本人的QQ",
    "heat": 588231,
    "search_query": "疑似加到了孙怡本人的QQ 微博热搜 2026年05月"
  },
  {
    "rank": 14,
    "title": "尼坤发福",
    "heat": 585439,
    "search_query": "尼坤发福 微博热搜 2026年05月"
  },
  {
    "rank": 15,
    "title": "女儿的100个橡皮",
    "heat": 576223,
    "search_query": "女儿的100个橡皮 微博热搜 2026年05月"
  }
]