[
  {
    "rank": 1,
    "title": "白鹿方六连辟谣",
    "heat": 9849583,
    "search_query": "白鹿方六连辟谣 微博热搜 2026年06月"
  },
  {
    "rank": 2,
    "title": "老外也疑惑中国为什么不参加世界杯",
    "heat": 1930280,
    "search_query": "老外也疑惑中国为什么不参加世界杯 微博热搜 2026年06月"
  },
  {
    "rank": 3,
    "title": "网信办发布公约整治涉企侵权信息",
    "heat": 1590551,
    "search_query": "网信办发布公约整治涉企侵权信息 微博热搜 2026年06月"
  },
  {
    "rank": 4,
    "title": "足球搭子有伊利",
    "heat": 0,
    "search_query": "足球搭子有伊利 微博热搜 2026年06月"
  },
  {
    "rank": 5,
    "title": "韩国vs捷克",
    "heat": 933585,
    "search_query": "韩国vs捷克 微博热搜 2026年06月"
  },
  {
    "rank": 6,
    "title": "上下嘴唇一碰差点把自己毒死",
    "heat": 875032,
    "search_query": "上下嘴唇一碰差点把自己毒死 微博热搜 2026年06月"
  },
  {
    "rank": 7,
    "title": "韩国2比1捷克",
    "heat": 793291,
    "search_query": "韩国2比1捷克 微博热搜 2026年06月"
  },
  {
    "rank": 8,
    "title": "神州租车 为热爱赴山海",
    "heat": 0,
    "search_query": "神州租车 为热爱赴山海 微博热搜 2026年06月"
  },
  {
    "rank": 9,
    "title": "第一次见丑得像人的狗",
    "heat": 730460,
    "search_query": "第一次见丑得像人的狗 微博热搜 2026年06月"
  },
  {
    "rank": 10,
    "title": "孙怡给了陈瑶60票",
    "heat": 597408,
    "search_query": "孙怡给了陈瑶60票 微博热搜 2026年06月"
  },
  {
    "rank": 11,
    "title": "浪姐四公个喜排名结果",
    "heat": 594949,
    "search_query": "浪姐四公个喜排名结果 微博热搜 2026年06月"
  },
  {
    "rank": 12,
    "title": "影石对大疆发起反诉",
    "heat": 579797,
    "search_query": "影石对大疆发起反诉 微博热搜 2026年06月"
  },
  {
    "rank": 13,
    "title": "白鹿学历",
    "heat": 9712503,
    "search_query": "白鹿学历 微博热搜 2026年06月"
  },
  {
    "rank": 14,
    "title": "陈立农这是干什么",
    "heat": 545411,
    "search_query": "陈立农这是干什么 微博热搜 2026年06月"
  },
  {
    "rank": 15,
    "title": "日本炸鸡店一锅油反复用66年",
    "heat": 542934,
    "search_query": "日本炸鸡店一锅油反复用66年 微博热搜 2026年06月"
  }
]