[
  {
    "rank": 1,
    "title": "阿根廷vs瑞士",
    "heat": 9188200,
    "search_query": "阿根廷vs瑞士 微博热搜 2026年07月"
  },
  {
    "rank": 2,
    "title": "阿根廷3比1瑞士",
    "heat": 4124594,
    "search_query": "阿根廷3比1瑞士 微博热搜 2026年07月"
  },
  {
    "rank": 3,
    "title": "防范应对台风巴威",
    "heat": 3225561,
    "search_query": "防范应对台风巴威 微博热搜 2026年07月"
  },
  {
    "rank": 4,
    "title": "李小冉再度携手欧迪芬",
    "heat": 0,
    "search_query": "李小冉再度携手欧迪芬 微博热搜 2026年07月"
  },
  {
    "rank": 5,
    "title": "巴威台风届变脸第一名",
    "heat": 3004589,
    "search_query": "巴威台风届变脸第一名 微博热搜 2026年07月"
  },
  {
    "rank": 6,
    "title": "瑞士 脏",
    "heat": 2345738,
    "search_query": "瑞士 脏 微博热搜 2026年07月"
  },
  {
    "rank": 7,
    "title": "6月新增新冠确诊7.9万例",
    "heat": 2320545,
    "search_query": "6月新增新冠确诊7.9万例 微博热搜 2026年07月"
  },
  {
    "rank": 8,
    "title": "世界杯四强",
    "heat": 2125607,
    "search_query": "世界杯四强 微博热搜 2026年07月"
  },
  {
    "rank": 9,
    "title": "阿尔瓦雷斯世界波",
    "heat": 1101614,
    "search_query": "阿尔瓦雷斯世界波 微博热搜 2026年07月"
  },
  {
    "rank": 10,
    "title": "王俊凯你要毁了丁程鑫吗",
    "heat": 1081520,
    "search_query": "王俊凯你要毁了丁程鑫吗 微博热搜 2026年07月"
  },
  {
    "rank": 11,
    "title": "迪丽热巴票房破2亿海报",
    "heat": 854129,
    "search_query": "迪丽热巴票房破2亿海报 微博热搜 2026年07月"
  },
  {
    "rank": 12,
    "title": "恩博洛哭了",
    "heat": 795512,
    "search_query": "恩博洛哭了 微博热搜 2026年07月"
  },
  {
    "rank": 13,
    "title": "哈兰德 全场梦游",
    "heat": 727395,
    "search_query": "哈兰德 全场梦游 微博热搜 2026年07月"
  },
  {
    "rank": 14,
    "title": "阿根廷瑞士 看力竭了",
    "heat": 599777,
    "search_query": "阿根廷瑞士 看力竭了 微博热搜 2026年07月"
  },
  {
    "rank": 15,
    "title": "王俊凯参加过黄晓明的婚礼",
    "heat": 564152,
    "search_query": "王俊凯参加过黄晓明的婚礼 微博热搜 2026年07月"
  }
]